alphalens/__init__.py
alphalens/_version.py
alphalens/performance.py
alphalens/plot_cn_name_map.py
alphalens/plotting.py
alphalens/tears.py
alphalens/utils.py
alphalens_tej-2.0.3.dist-info/licenses/LICENSE
alphalens_tej-2.0.3.dist-info/METADATA
alphalens_tej-2.0.3.dist-info/WHEEL
alphalens_tej-2.0.3.dist-info/top_level.txt
alphalens_tej-2.0.3.dist-info/RECORD
